cz_fogoprobr.py
commitizen_cz_fogoprobr-1.0.2.dist-info/METADATA
commitizen_cz_fogoprobr-1.0.2.dist-info/WHEEL
commitizen_cz_fogoprobr-1.0.2.dist-info/top_level.txt
commitizen_cz_fogoprobr-1.0.2.dist-info/RECORD
