Metadata-Version: 2.1
Name: commitizen-cz-fogoprobr
Version: 1.0.2
Summary: UNKNOWN
Home-page: https://github.com/melattofogo/cz-fogoprobr
License: MIT
Platform: UNKNOWN
Requires-Dist: commitizen (>=2.21.2)
